Workbook

Sheet Overview
A2: Czechoslovakia’s effective exchange rates | B2: Czechoslovakia’s effective exchange rates | C2: Czechoslovakia’s effective exchange rates | D2: Czechoslovakia’s effective exchange rates | E2: Czechoslovakia’s effective exchange rates | F2: Czechoslovakia’s effective exchange rates | G2: Czechoslovakia’s effective exchange rates | H2: Czechoslovakia’s effective exchange rates | I2: Czechoslovakia’s effective exchange rates | J2: Czechoslovakia’s effective exchange rates | K2: Czechoslovakia’s effective exchange rates | L2: Czechoslovakia’s effective exchange rates | M2: Czechoslovakia’s effective exchange rates | N2: Czechoslovakia’s effective exchange rates
A3: The Crown Against the World. Annual dataset, 1920–1938. | B3: The Crown Against the World. Annual dataset, 1920–1938. | C3: The Crown Against the World. Annual dataset, 1920–1938. | D3: The Crown Against the World. Annual dataset, 1920–1938. | E3: The Crown Against the World. Annual dataset, 1920–1938. | F3: The Crown Against the World. Annual dataset, 1920–1938. | G3: The Crown Against the World. Annual dataset, 1920–1938. | H3: The Crown Against the World. Annual dataset, 1920–1938. | I3: The Crown Against the World. Annual dataset, 1920–1938. | J3: The Crown Against the World. Annual dataset, 1920–1938. | K3: The Crown Against the World. Annual dataset, 1920–1938. | L3: The Crown Against the World. Annual dataset, 1920–1938. | M3: The Crown Against the World. Annual dataset, 1920–1938. | N3: The Crown Against the World. Annual dataset, 1920–1938.
A6: How to read the indices | B6: How to read the indices | C6: How to read the indices | D6: How to read the indices | E6: How to read the indices | F6: How to read the indices | G6: How to read the indices | H6: How to read the indices | I6: How to read the indices | K6: Adam Dittrich | L6: Adam Dittrich | M6: Adam Dittrich | N6: Adam Dittrich
A7: Base: 1929 = 100 for every NEER and REER series. | B7: Base: 1929 = 100 for every NEER and REER series. | C7: Base: 1929 = 100 for every NEER and REER series. | D7: Base: 1929 = 100 for every NEER and REER series. | E7: Base: 1929 = 100 for every NEER and REER series. | F7: Base: 1929 = 100 for every NEER and REER series. | G7: Base: 1929 = 100 for every NEER and REER series. | H7: Base: 1929 = 100 for every NEER and REER series. | I7: Base: 1929 = 100 for every NEER and REER series. | K7: Release: 22 October 2026 | L7: Release: 22 October 2026 | M7: Release: 22 October 2026 | N7: Release: 22 October 2026
A8: Higher NEER means nominal depreciation of the crown. | B8: Higher NEER means nominal depreciation of the crown. | C8: Higher NEER means nominal depreciation of the crown. | D8: Higher NEER means nominal depreciation of the crown. | E8: Higher NEER means nominal depreciation of the crown. | F8: Higher NEER means nominal depreciation of the crown. | G8: Higher NEER means nominal depreciation of the crown. | H8: Higher NEER means nominal depreciation of the crown. | I8: Higher NEER means nominal depreciation of the crown. | K8: 14 trading partners Annual observations | L8: 14 trading partners Annual observations | M8: 14 trading partners Annual observations | N8: 14 trading partners Annual observations
A9: Higher REER means real depreciation and stronger measured price competitiveness. | B9: Higher REER means real depreciation and stronger measured price competitiveness. | C9: Higher REER means real depreciation and stronger measured price competitiveness. | D9: Higher REER means real depreciation and stronger measured price competitiveness. | E9: Higher REER means real depreciation and stronger measured price competitiveness. | F9: Higher REER means real depreciation and stronger measured price competitiveness. | G9: Higher REER means real depreciation and stronger measured price competitiveness. | H9: Higher REER means real depreciation and stronger measured price competitiveness. | I9: Higher REER means real depreciation and stronger measured price competitiveness. | J9: Higher REER means real depreciation and stronger measured price competitiveness. | K9: 14 trading partners Annual observations | L9: 14 trading partners Annual observations | M9: 14 trading partners Annual observations | N9: 14 trading partners Annual observations
A10: NEER: 1920–1938. REER: 1923–1938. Analytical core: 1925–1938. | B10: NEER: 1920–1938. REER: 1923–1938. Analytical core: 1925–1938. | C10: NEER: 1920–1938. REER: 1923–1938. Analytical core: 1925–1938. | D10: NEER: 1920–1938. REER: 1923–1938. Analytical core: 1925–1938. | E10: NEER: 1920–1938. REER: 1923–1938. Analytical core: 1925–1938. | F10: NEER: 1920–1938. REER: 1923–1938. Analytical core: 1925–1938. | G10: NEER: 1920–1938. REER: 1923–1938. Analytical core: 1925–1938. | H10: NEER: 1920–1938. REER: 1923–1938. Analytical core: 1925–1938. | I10: NEER: 1920–1938. REER: 1923–1938. Analytical core: 1925–1938. | J10: NEER: 1920–1938. REER: 1923–1938. Analytical core: 1925–1938. | K10: NEER: 1920–1938. REER: 1923–1938. Analytical core: 1925–1938. | L10: NEER: 1920–1938. REER: 1923–1938. Analytical core: 1925–1938. | M10: NEER: 1920–1938. REER: 1923–1938. Analytical core: 1925–1938. | N10: NEER: 1920–1938. REER: 1923–1938. Analytical core: 1925–1938.
A12: Explore the dataset | B12: Explore the dataset | C12: Explore the dataset | D12: Explore the dataset | E12: Explore the dataset | F12: Explore the dataset | G12: Explore the dataset | H12: Explore the dataset | I12: Explore the dataset | J12: Explore the dataset | L12: Data tables start in row 1. Use the header filters to select a year, method or partner. Blank REER cells mean unavailable. | M12: Data tables start in row 1. Use the header filters to select a year, method or partner. Blank REER cells mean unavailable. | N12: Data tables start in row 1. Use the header filters to select a year, method or partner. Blank REER cells mean unavailable.
A13: Annual EER | D13: Six preferred indices, with total-trade, export and import weights. | E13: Six preferred indices, with total-trade, export and import weights. | F13: Six preferred indices, with total-trade, export and import weights. | G13: Six preferred indices, with total-trade, export and import weights. | H13: Six preferred indices, with total-trade, export and import weights. | I13: Six preferred indices, with total-trade, export and import weights. | J13: Six preferred indices, with total-trade, export and import weights. | L13: Data tables start in row 1. Use the header filters to select a year, method or partner. Blank REER cells mean unavailable. | M13: Data tables start in row 1. Use the header filters to select a year, method or partner. Blank REER cells mean unavailable. | N13: Data tables start in row 1. Use the header filters to select a year, method or partner. Blank REER cells mean unavailable.
A14: All series | D14: All 26 index variants in one filterable table. | E14: All 26 index variants in one filterable table. | F14: All 26 index variants in one filterable table. | G14: All 26 index variants in one filterable table. | H14: All 26 index variants in one filterable table. | I14: All 26 index variants in one filterable table. | J14: All 26 index variants in one filterable table. | L14: Data tables start in row 1. Use the header filters to select a year, method or partner. Blank REER cells mean unavailable. | M14: Data tables start in row 1. Use the header filters to select a year, method or partner. Blank REER cells mean unavailable. | N14: Data tables start in row 1. Use the header filters to select a year, method or partner. Blank REER cells mean unavailable.
A15: Partner weights | D15: Annual shares for each of the 14 included partners. | E15: Annual shares for each of the 14 included partners. | F15: Annual shares for each of the 14 included partners. | G15: Annual shares for each of the 14 included partners. | H15: Annual shares for each of the 14 included partners. | I15: Annual shares for each of the 14 included partners. | J15: Annual shares for each of the 14 included partners. | L15: Data tables start in row 1. Use the header filters to select a year, method or partner. Blank REER cells mean unavailable. | M15: Data tables start in row 1. Use the header filters to select a year, method or partner. Blank REER cells mean unavailable. | N15: Data tables start in row 1. Use the header filters to select a year, method or partner. Blank REER cells mean unavailable.
A16: Basket coverage | D16: The share of national trade represented by the basket. | E16: The share of national trade represented by the basket. | F16: The share of national trade represented by the basket. | G16: The share of national trade represented by the basket. | H16: The share of national trade represented by the basket. | I16: The share of national trade represented by the basket. | J16: The share of national trade represented by the basket. | L16: Data tables start in row 1. Use the header filters to select a year, method or partner. Blank REER cells mean unavailable. | M16: Data tables start in row 1. Use the header filters to select a year, method or partner. Blank REER cells mean unavailable. | N16: Data tables start in row 1. Use the header filters to select a year, method or partner. Blank REER cells mean unavailable.
A17: Definitions | D17: Variables, methods, source information and citation guidance. | E17: Variables, methods, source information and citation guidance. | F17: Variables, methods, source information and citation guidance. | G17: Variables, methods, source information and citation guidance. | H17: Variables, methods, source information and citation guidance. | I17: Variables, methods, source information and citation guidance. | J17: Variables, methods, source information and citation guidance. | L17: Data tables start in row 1. Use the header filters to select a year, method or partner. Blank REER cells mean unavailable. | M17: Data tables start in row 1. Use the header filters to select a year, method or partner. Blank REER cells mean unavailable. | N17: Data tables start in row 1. Use the header filters to select a year, method or partner. Blank REER cells mean unavailable.
A38: Preferred series: geometric chains with current-year weights based on exports plus imports. | B38: Preferred series: geometric chains with current-year weights based on exports plus imports. | C38: Preferred series: geometric chains with current-year weights based on exports plus imports. | D38: Preferred series: geometric chains with current-year weights based on exports plus imports. | E38: Preferred series: geometric chains with current-year weights based on exports plus imports. | F38: Preferred series: geometric chains with current-year weights based on exports plus imports. | G38: Preferred series: geometric chains with current-year weights based on exports plus imports. | H38: Preferred series: geometric chains with current-year weights based on exports plus imports. | I38: Preferred series: geometric chains with current-year weights based on exports plus imports. | J38: Preferred series: geometric chains with current-year weights based on exports plus imports. | K38: Preferred series: geometric chains with current-year weights based on exports plus imports. | L38: Preferred series: geometric chains with current-year weights based on exports plus imports. | M38: Preferred series: geometric chains with current-year weights based on exports plus imports. | N38: Preferred series: geometric chains with current-year weights based on exports plus imports.
A59: Both charts show the analytical core. The complete early extension is retained in the data tables. | B59: Both charts show the analytical core. The complete early extension is retained in the data tables. | C59: Both charts show the analytical core. The complete early extension is retained in the data tables. | D59: Both charts show the analytical core. The complete early extension is retained in the data tables. | E59: Both charts show the analytical core. The complete early extension is retained in the data tables. | F59: Both charts show the analytical core. The complete early extension is retained in the data tables. | G59: Both charts show the analytical core. The complete early extension is retained in the data tables. | H59: Both charts show the analytical core. The complete early extension is retained in the data tables. | I59: Both charts show the analytical core. The complete early extension is retained in the data tables. | J59: Both charts show the analytical core. The complete early extension is retained in the data tables. | K59: Both charts show the analytical core. The complete early extension is retained in the data tables. | L59: Both charts show the analytical core. The complete early extension is retained in the data tables. | M59: Both charts show the analytical core. The complete early extension is retained in the data tables. | N59: Both charts show the analytical core. The complete early extension is retained in the data tables.
A61: Chart data for the analytical core
A63: Year | B63: NEER total trade | C63: REER total trade | D63: NEER exports | E63: REER exports | F63: NEER imports | G63: REER imports
A64: =TEXT('Annual EER'!A7,"0") -> 1925 | B64: ='Annual EER'!B7 -> 101.86477 | C64: ='Annual EER'!C7 -> 99.92679 | D64: ='Annual EER'!D7 -> 99.844539 | E64: ='Annual EER'!E7 -> 98.89 | F64: ='Annual EER'!F7 -> 104.3559 | G64: ='Annual EER'!G7 -> 101.20056
A65: =TEXT('Annual EER'!A8,"0") -> 1926 | B65: ='Annual EER'!B8 -> 97.656426 | C65: ='Annual EER'!C8 -> 98.547891 | D65: ='Annual EER'!D8 -> 97.746367 | E65: ='Annual EER'!E8 -> 98.518217 | F65: ='Annual EER'!F8 -> 97.558121 | G65: ='Annual EER'!G8 -> 98.597179
A66: =TEXT('Annual EER'!A9,"0") -> 1927 | B66: ='Annual EER'!B9 -> 99.927302 | C66: ='Annual EER'!C9 -> 97.054763 | D66: ='Annual EER'!D9 -> 99.959572 | E66: ='Annual EER'!E9 -> 97.384426 | F66: ='Annual EER'!F9 -> 99.893032 | G66: ='Annual EER'!G9 -> 96.705739
A67: =TEXT('Annual EER'!A10,"0") -> 1928 | B67: ='Annual EER'!B10 -> 100.15885 | C67: ='Annual EER'!C10 -> 97.89238 | D67: ='Annual EER'!D10 -> 100.1702 | E67: ='Annual EER'!E10 -> 98.008338 | F67: ='Annual EER'!F10 -> 100.14735 | G67: ='Annual EER'!G10 -> 97.774949
A68: =TEXT('Annual EER'!A11,"0") -> 1929 | B68: ='Annual EER'!B11 -> 100 | C68: ='Annual EER'!C11 -> 100 | D68: ='Annual EER'!D11 -> 100 | E68: ='Annual EER'!E11 -> 100 | F68: ='Annual EER'!F11 -> 100 | G68: ='Annual EER'!G11 -> 100
A69: =TEXT('Annual EER'!A12,"0") -> 1930 | B69: ='Annual EER'!B12 -> 100.08018 | C69: ='Annual EER'!C12 -> 98.11827 | D69: ='Annual EER'!D12 -> 100.09421 | E69: ='Annual EER'!E12 -> 98.148581 | F69: ='Annual EER'!F12 -> 100.06502 | G69: ='Annual EER'!G12 -> 98.085516
A70: =TEXT('Annual EER'!A13,"0") -> 1931 | B70: ='Annual EER'!B13 -> 99.1424 | C70: ='Annual EER'!C13 -> 95.184066 | D70: ='Annual EER'!D13 -> 98.905275 | E70: ='Annual EER'!E13 -> 95.689463 | F70: ='Annual EER'!F13 -> 99.39059 | G70: ='Annual EER'!G13 -> 94.657186
A71: =TEXT('Annual EER'!A14,"0") -> 1932 | B71: ='Annual EER'!B14 -> 96.499255 | C71: ='Annual EER'!C14 -> 89.305153 | D71: ='Annual EER'!D14 -> 95.458547 | E71: ='Annual EER'!E14 -> 89.59561 | F71: ='Annual EER'!F14 -> 97.447695 | G71: ='Annual EER'!G14 -> 88.967725
A72: =TEXT('Annual EER'!A15,"0") -> 1933 | B72: ='Annual EER'!B15 -> 93.650584 | C72: ='Annual EER'!C15 -> 85.108992 | D72: ='Annual EER'!D15 -> 92.9066 | E72: ='Annual EER'!E15 -> 85.613868 | F72: ='Annual EER'!F15 -> 94.30298 | G72: ='Annual EER'!G15 -> 84.563824
A73: =TEXT('Annual EER'!A16,"0") -> 1934 | B73: ='Annual EER'!B16 -> 105.70766 | C73: ='Annual EER'!C16 -> 95.843124 | D73: ='Annual EER'!D16 -> 104.60209 | E73: ='Annual EER'!E16 -> 96.097097 | F73: ='Annual EER'!F16 -> 106.75697 | G73: ='Annual EER'!G16 -> 95.58986
A74: =TEXT('Annual EER'!A17,"0") -> 1935 | B74: ='Annual EER'!B17 -> 107.17947 | C74: ='Annual EER'!C17 -> 93.352658 | D74: ='Annual EER'!D17 -> 106.06234 | E74: ='Annual EER'!E17 -> 93.704519 | F74: ='Annual EER'!F17 -> 108.23858 | G74: ='Annual EER'!G17 -> 92.97853
A75: =TEXT('Annual EER'!A18,"0") -> 1936 | B75: ='Annual EER'!B18 -> 109.03473 | C75: ='Annual EER'!C18 -> 95.97154 | D75: ='Annual EER'!D18 -> 107.86995 | E75: ='Annual EER'!E18 -> 96.285061 | F75: ='Annual EER'!F18 -> 110.14208 | G75: ='Annual EER'!G18 -> 95.636445
... A77: =TEXT('Annual EER'!A20,"0") -> 1938 | B77: ='Annual EER'!B20 -> 111.94319 | C77: ='Annual EER'!C20 -> 100.33391 | D77: ='Annual EER'!D20 -> 111.05248 | E77: ='Annual EER'!E20 -> 100.64961 | F77: ='Annual EER'!F20 -> 112.7017 | G77: ='Annual EER'!G20 -> 99.989901

Sheet Annual EER
A1: year | B1: NEER_total | C1: REER_total | D1: NEER_exports | E1: REER_exports | F1: NEER_imports | G1: REER_imports | H1: sample
A2: 1920 | B2: 8901771.3 | D2: 1637561.3 | F2: 55235118 | H2: pre-stabilisation extension
A3: 1921 | B3: 6375400.3 | D3: 1032462.4 | F3: 47032319 | H3: pre-stabilisation extension
A4: 1922 | B4: 1299482.7 | D4: 187221.52 | F4: 11458821 | H4: pre-stabilisation extension
A5: 1923 | B5: 96943.56 | C5: 2.9014779e+08 | D5: 19166.887 | E5: 7804452.3 | F5: 574887.5 | G5: 1.5331847e+10 | H5: pre-stabilisation extension
A6: 1924 | B6: 103.18116 | C6: 99.694933 | D6: 100.51168 | E6: 98.206624 | F6: 106.3976 | G6: 101.45931 | H6: pre-stabilisation extension
A7: 1925 | B7: 101.86477 | C7: 99.92679 | D7: 99.844539 | E7: 98.89 | F7: 104.3559 | G7: 101.20056 | H7: analytical core
A8: 1926 | B8: 97.656426 | C8: 98.547891 | D8: 97.746367 | E8: 98.518217 | F8: 97.558121 | G8: 98.597179 | H8: analytical core
A9: 1927 | B9: 99.927302 | C9: 97.054763 | D9: 99.959572 | E9: 97.384426 | F9: 99.893032 | G9: 96.705739 | H9: analytical core
A10: 1928 | B10: 100.15885 | C10: 97.89238 | D10: 100.1702 | E10: 98.008338 | F10: 100.14735 | G10: 97.774949 | H10: analytical core
A11: 1929 | B11: 100 | C11: 100 | D11: 100 | E11: 100 | F11: 100 | G11: 100 | H11: analytical core
A12: 1930 | B12: 100.08018 | C12: 98.11827 | D12: 100.09421 | E12: 98.148581 | F12: 100.06502 | G12: 98.085516 | H12: analytical core
A13: 1931 | B13: 99.1424 | C13: 95.184066 | D13: 98.905275 | E13: 95.689463 | F13: 99.39059 | G13: 94.657186 | H13: analytical core
A14: 1932 | B14: 96.499255 | C14: 89.305153 | D14: 95.458547 | E14: 89.59561 | F14: 97.447695 | G14: 88.967725 | H14: analytical core
A15: 1933 | B15: 93.650584 | C15: 85.108992 | D15: 92.9066 | E15: 85.613868 | F15: 94.30298 | G15: 84.563824 | H15: analytical core
A16: 1934 | B16: 105.70766 | C16: 95.843124 | D16: 104.60209 | E16: 96.097097 | F16: 106.75697 | G16: 95.58986 | H16: analytical core
... A20: 1938 | B20: 111.94319 | C20: 100.33391 | D20: 111.05248 | E20: 100.64961 | F20: 112.7017 | G20: 99.989901 | H20: analytical core

Sheet All series
A1: year | B1: trade_basis | C1: method | D1: NEER | E1: REER | F1: sample
A2: 1920 | B2: TWEER | C2: paasche | D2: 8901771.3 | F2: pre-stabilisation extension
A3: 1920 | B3: TWEER | C3: laspeyres | D3: 8811848.3 | F3: pre-stabilisation extension
A4: 1920 | B4: TWEER | C4: tornqvist | D4: 8856695.7 | F4: pre-stabilisation extension
A5: 1920 | B5: TWEER | C5: fixed1929 | D5: 10229991 | F5: pre-stabilisation extension
A6: 1920 | B6: XEER | C6: paasche | D6: 1637561.3 | F6: pre-stabilisation extension
A7: 1920 | B7: XEER | C7: laspeyres | D7: 2205254 | F7: pre-stabilisation extension
A8: 1920 | B8: XEER | C8: tornqvist | D8: 1900325.9 | F8: pre-stabilisation extension
A9: 1920 | B9: XEER | C9: fixed1929 | D9: 1331226.8 | F9: pre-stabilisation extension
A10: 1920 | B10: MEER | C10: paasche | D10: 55235118 | F10: pre-stabilisation extension
A11: 1920 | B11: MEER | C11: laspeyres | D11: 49385682 | F11: pre-stabilisation extension
A12: 1920 | B12: MEER | C12: tornqvist | D12: 52228575 | F12: pre-stabilisation extension
A13: 1920 | B13: MEER | C13: fixed1929 | D13: 80876311 | F13: pre-stabilisation extension
... A40: 1922 | B40: TWEER | C40: direct_current | D40: 241462.09 | F40: pre-stabilisation extension
A41: 1923 | B41: TWEER | C41: paasche | D41: 96943.56 | E41: 2.9014779e+08 | F41: pre-stabilisation extension
A42: 1923 | B42: TWEER | C42: laspeyres | D42: 128237.8 | E42: 6.1812354e+08 | F42: pre-stabilisation extension
A43: 1923 | B43: TWEER | C43: tornqvist | D43: 111498.11 | E43: 4.2349401e+08 | F43: pre-stabilisation extension
A44: 1923 | B44: TWEER | C44: fixed1929 | D44: 114784.1 | E44: 3.7410748e+08 | F44: pre-stabilisation extension
A45: 1923 | B45: XEER | C45: paasche | D45: 19166.887 | E45: 7804452.3 | F45: pre-stabilisation extension
A46: 1923 | B46: XEER | C46: laspeyres | D46: 23641.49 | E46: 13326915 | F46: pre-stabilisation extension
A47: 1923 | B47: XEER | C47: tornqvist | D47: 21286.939 | E47: 10198494 | F47: pre-stabilisation extension
A48: 1923 | B48: XEER | C48: fixed1929 | D48: 21502.881 | E48: 9072412.3 | F48: pre-stabilisation extension
A49: 1923 | B49: MEER | C49: paasche | D49: 574887.5 | E49: 1.5331847e+10 | F49: pre-stabilisation extension
A50: 1923 | B50: MEER | C50: laspeyres | D50: 1064022.2 | E50: 7.571139e+10 | F50: pre-stabilisation extension
A51: 1923 | B51: MEER | C51: tornqvist | D51: 782108.1 | E51: 3.4070448e+10 | F51: pre-stabilisation extension
A52: 1923 | B52: MEER | C52: fixed1929 | D52: 627173.86 | E52: 1.6245964e+10 | F52: pre-stabilisation extension
... A248: 1938 | B248: TWEER | C248: direct_current | D248: 106.7454 | E248: 96.385958 | F248: analytical core

Sheet Partner weights
A1: year | B1: partner | C1: total_trade_weight | D1: export_weight | E1: import_weight
A2: 1920 | B2: Austria | C2: 0.27360368 | D2: 0.37649382 | E2: 0.1463485
A3: 1920 | B3: Belgium-Luxembourg | C3: 0.025228922 | D3: 0.0052512312 | E3: 0.049937458
A4: 1920 | B4: France | C4: 0.071600241 | D4: 0.092343872 | E4: 0.045944386
A5: 1920 | B5: Germany | C5: 0.19615326 | D5: 0.13622083 | E5: 0.27027807
A6: 1920 | B6: Hungary | C6: 0.068137448 | D6: 0.097711797 | E6: 0.031559704
A7: 1920 | B7: Italy | C7: 0.049554507 | D7: 0.050606309 | E7: 0.048253632
A8: 1920 | B8: Netherlands | C8: 0.040284545 | D8: 0.021666191 | E8: 0.063311845
A9: 1920 | B9: Poland | C9: 0.039230652 | D9: 0.055429662 | E9: 0.019195612
A10: 1920 | B10: Romania | C10: 0.022368354 | D10: 0.028473342 | E10: 0.014817666
A11: 1920 | B11: Sweden | C11: 0.014023237 | D11: 0.01112483 | E11: 0.017608005
A12: 1920 | B12: Switzerland | C12: 0.029917673 | D12: 0.029795875 | E12: 0.030068315
A13: 1920 | B13: United Kingdom | C13: 0.039187636 | D13: 0.031624081 | E13: 0.048542288
... A267: 1938 | B267: Yugoslavia | C267: 0.071039492 | D267: 0.08708293 | E267: 0.051709758

Sheet Basket coverage
A1: year | B1: export_coverage | C1: import_coverage | D1: total_trade_coverage
A2: 1920 | B2: 0.9016 | C2: 0.8693 | D2: 0.8868
A3: 1921 | B3: 0.8871 | C3: 0.8127 | D3: 0.854
A4: 1922 | B4: 0.8419 | C4: 0.8038 | D4: 0.8264
A5: 1923 | B5: 0.8177 | C5: 0.8381 | D5: 0.8266
A6: 1924 | B6: 0.9029 | C6: 0.8844 | D6: 0.894
A7: 1925 | B7: 0.8728 | C7: 0.8817 | D7: 0.8771
A8: 1926 | B8: 0.8524 | C8: 0.8295 | D8: 0.8419
A9: 1927 | B9: 0.8773 | C9: 0.8851 | D9: 0.881
A10: 1928 | B10: 0.8569 | C10: 0.8699 | D10: 0.8631
A11: 1929 | B11: 0.849 | C11: 0.8601 | D11: 0.8545
A12: 1930 | B12: 0.8426 | C12: 0.8668 | D12: 0.8541
A13: 1931 | B13: 0.8095 | C13: 0.8622 | D13: 0.8345
... A20: 1938 | B20: 0.8486 | C20: 0.8701 | D20: 0.8582

Sheet Definitions
A1: section | B1: term | C1: definition
A2: Dataset | B2: Paper | C2: Adam Dittrich. The Crown Against the World: Reconstructing Czechoslovakia’s Effective Exchange Rates, 1920–1938. Companion dataset for the manuscript prepared for Statistika: Statistics and Economy Journal.
A3: Dataset | B3: Workbook release | C3: 22 October 2026. Reader edition of the final harmonised series in the supplied publication package. Original index values are retained at full available precision.
A4: Dataset | B4: Frequency and coverage | C4: Annual calendar-year observations. NEER is available for 1920–1938 and CPI-based REER for 1923–1938. The analytical core is 1925–1938.
A5: Dataset | B5: Index base | C5: All NEER and REER variants equal 100 in 1929. Values are index points, not exchange-rate quotations or percentages.
A6: Dataset | B6: Direction | C6: An increase in NEER means nominal depreciation of the Czechoslovak crown. An increase in REER means real depreciation and stronger measured price competitiveness.
A7: Dataset | B7: Missing values | C7: Empty REER cells in 1920–1922 mean unavailable, not zero. No missing REER values have been interpolated.
A8: Dataset | B8: Precision | C8: Index cells display two decimal places. Their stored numeric values retain the source precision. Years are stored as integers.
A9: Annual EER | B9: year | C9: Calendar year, 1920–1938.
A10: Annual EER | B10: NEER_total / REER_total | C10: Preferred nominal and real effective exchange rates. Current-year weighted geometric chains based on total trade, with 1929 = 100. Source fields: NEER_TWEER_paasche and REER_TWEER_paasche.
A11: Annual EER | B11: NEER_exports / REER_exports | C11: Current-year weighted nominal and real chains using export shares. Source fields: NEER_XEER_paasche and REER_XEER_paasche.
A12: Annual EER | B12: NEER_imports / REER_imports | C12: Current-year weighted nominal and real chains using import shares. Source fields: NEER_MEER_paasche and REER_MEER_paasche.
... A40: Citation | B40: Deposit scope | C40: The DOI identifies the related deposit cited by the manuscript. This workbook is a separately packaged reader edition and does not carry a newly assigned DOI.
